pascal/__init__.py
pascal/__main__.py
pascal_tri-1.2.6.data/data/README.md/README.md
pascal_tri-1.2.6.data/data/VERSION/VERSION
pascal_tri-1.2.6.dist-info/LICENSE
pascal_tri-1.2.6.dist-info/METADATA
pascal_tri-1.2.6.dist-info/WHEEL
pascal_tri-1.2.6.dist-info/entry_points.txt
pascal_tri-1.2.6.dist-info/top_level.txt
pascal_tri-1.2.6.dist-info/RECORD
