Metadata-Version: 2.1
Name: pascal-tri
Version: 1.2.6
Summary: Module for generating and printing Pascal's Triangle
Home-page: https://github.com/jack-mil/pascal
Author: jack-mil
License: MIT
Platform: UNKNOWN
Classifier: Programming Language :: Python :: 3.9
Classifier: License :: OSI Approved :: MIT License
Classifier: Operating System :: OS Independent
Requires-Python: >=3.9
License-File: LICENSE
